google/shopping/merchant_conversions/__init__.py
google/shopping/merchant_conversions/gapic_version.py
google/shopping/merchant_conversions/py.typed
google/shopping/merchant_conversions_v1/__init__.py
google/shopping/merchant_conversions_v1/gapic_metadata.json
google/shopping/merchant_conversions_v1/gapic_version.py
google/shopping/merchant_conversions_v1/py.typed
google/shopping/merchant_conversions_v1/services/__init__.py
google/shopping/merchant_conversions_v1/services/conversion_sources_service/__init__.py
google/shopping/merchant_conversions_v1/services/conversion_sources_service/async_client.py
google/shopping/merchant_conversions_v1/services/conversion_sources_service/client.py
google/shopping/merchant_conversions_v1/services/conversion_sources_service/pagers.py
google/shopping/merchant_conversions_v1/services/conversion_sources_service/transports/__init__.py
google/shopping/merchant_conversions_v1/services/conversion_sources_service/transports/base.py
google/shopping/merchant_conversions_v1/services/conversion_sources_service/transports/grpc.py
google/shopping/merchant_conversions_v1/services/conversion_sources_service/transports/grpc_asyncio.py
google/shopping/merchant_conversions_v1/services/conversion_sources_service/transports/rest.py
google/shopping/merchant_conversions_v1/services/conversion_sources_service/transports/rest_base.py
google/shopping/merchant_conversions_v1/types/__init__.py
google/shopping/merchant_conversions_v1/types/conversionsources.py
google/shopping/merchant_conversions_v1beta/__init__.py
google/shopping/merchant_conversions_v1beta/gapic_metadata.json
google/shopping/merchant_conversions_v1beta/gapic_version.py
google/shopping/merchant_conversions_v1beta/py.typed
google/shopping/merchant_conversions_v1beta/services/__init__.py
google/shopping/merchant_conversions_v1beta/services/conversion_sources_service/__init__.py
google/shopping/merchant_conversions_v1beta/services/conversion_sources_service/async_client.py
google_shopping_merchant_conversions-1.2.0.dist-info/licenses/LICENSE
google_shopping_merchant_conversions-1.2.0.dist-info/METADATA
google_shopping_merchant_conversions-1.2.0.dist-info/WHEEL
google_shopping_merchant_conversions-1.2.0.dist-info/top_level.txt
google_shopping_merchant_conversions-1.2.0.dist-info/RECORD
